{"web":{"client_id":"116522930461-ruc3d78t0cnknem7pa5n7nk2cb0j0j4f.apps.googleusercontent.com","project_id":"kwola-cloud","auth_uri":"https://accounts.google.com/o/oauth2/auth","token_uri":"https://oauth2.googleapis.com/token","auth_provider_x509_cert_url":"https://www.googleapis.com/oauth2/v1/certs","client_secret":"18BSwW5ATUsKMW08_BejevE4","redirect_uris":["https://app.kwola.io/api/marketing_auth","https://staging.kwola.io/api/marketing_auth","https://demo.kwola.io/api/marketing_auth","https://testing.kwola.io/api/marketing_auth","http://localhost:8000/api/marketing_auth"],"javascript_origins":["https://app.kwola.io","https://staging.kwola.io","https://demo.kwola.io","https://testing.kwola.io","http://localhost:8000"]}}